aiopoke/__init__.py
aiopoke/__main__.py
aiopoke/aiopoke_client.py
aiopoke/http_client.py
aiopoke/py.typed
aiopoke/objects/__init__.py
aiopoke/objects/resources/__init__.py
aiopoke/objects/resources/berries/__init__.py
aiopoke/objects/resources/berries/berry.py
aiopoke/objects/resources/berries/berry_firmness.py
aiopoke/objects/resources/berries/berry_flavor.py
aiopoke/objects/resources/contests/__init__.py
aiopoke/objects/resources/contests/contest_effect.py
aiopoke/objects/resources/contests/contest_type.py
aiopoke/objects/resources/contests/super_contest_effect.py
aiopoke/objects/resources/encounters/__init__.py
aiopoke/objects/resources/encounters/encounter_condition.py
aiopoke/objects/resources/encounters/encounter_condition_value.py
aiopoke/objects/resources/encounters/encounter_method.py
aiopoke/objects/resources/evolutions/__init__.py
aiopoke/objects/resources/evolutions/evolution_chain.py
aiopoke/objects/resources/evolutions/evolution_trigger.py
aiopoke/objects/resources/games/__init__.py
aiopoke/objects/resources/games/generation.py
aiopoke/objects/resources/games/pokedex.py
aiopoke/objects/resources/games/version.py
aiopoke/objects/resources/games/version_group.py
aiopoke/objects/resources/items/__init__.py
aiopoke/objects/resources/items/item.py
aiopoke/objects/resources/items/item_attribute.py
aiopoke/objects/resources/items/item_category.py
aiopoke/objects/resources/items/item_fling_effect.py
aiopoke/objects/resources/items/item_pocket.py
aiopoke/objects/resources/locations/__init__.py
aiopoke/objects/resources/locations/location.py
aiopoke/objects/resources/locations/location_area.py
aiopoke/objects/resources/locations/pal_park_area.py
aiopoke/objects/resources/locations/region.py
aiopoke/objects/resources/machines/__init__.py
aiopoke/objects/resources/machines/machine.py
aiopoke/objects/resources/moves/__init__.py
aiopoke/objects/resources/moves/move.py
aiopoke/objects/resources/moves/move_ailment.py
aiopokeapi-0.1.11.dist-info/LICENSE
aiopokeapi-0.1.11.dist-info/METADATA
aiopokeapi-0.1.11.dist-info/WHEEL
aiopokeapi-0.1.11.dist-info/top_level.txt
aiopokeapi-0.1.11.dist-info/RECORD
